webassets_babel/__init__.py
webassets_babel-0.3.0.dist-info/DESCRIPTION.rst
webassets_babel-0.3.0.dist-info/METADATA
webassets_babel-0.3.0.dist-info/metadata.json
webassets_babel-0.3.0.dist-info/RECORD
webassets_babel-0.3.0.dist-info/top_level.txt
webassets_babel-0.3.0.dist-info/WHEEL
