Metadata-Version: 2.0
Name: webassets-babel
Version: 0.3.0
Summary: Babel filter for Webassets
Home-page: https://github.com/lyapun/webassets-babel
Author: Taras Lyapun
Author-email: taraslyapun@gmail.com
License: BSD
Keywords: webassets babel
Platform: UNKNOWN
Classifier: Development Status :: 2 - Pre-Alpha
Classifier: Intended Audience :: Developers
Classifier: License :: OSI Approved :: BSD License
Classifier: Natural Language :: English
Classifier: Programming Language :: Python :: 2
Classifier: Programming Language :: Python :: 2.6
Classifier: Programming Language :: Python :: 2.7
Classifier: Programming Language :: Python :: 3
Classifier: Programming Language :: Python :: 3.3
Classifier: Programming Language :: Python :: 3.4
Classifier: Programming Language :: Python :: 3.5
Requires-Dist: webassets
